deep_translator/__init__.py
deep_translator/__main__.py
deep_translator/base.py
deep_translator/chatgpt.py
deep_translator/cli.py
deep_translator/constants.py
deep_translator/deepl.py
deep_translator/detection.py
deep_translator/engines.py
deep_translator/exceptions.py
deep_translator/google.py
deep_translator/libre.py
deep_translator/linguee.py
deep_translator/microsoft.py
deep_translator/mymemory.py
deep_translator/papago.py
deep_translator/pons.py
deep_translator/qcri.py
deep_translator/validate.py
deep_translator/yandex.py
deep_translator-1.11.0.dist-info/LICENSE
deep_translator-1.11.0.dist-info/METADATA
deep_translator-1.11.0.dist-info/WHEEL
deep_translator-1.11.0.dist-info/entry_points.txt
deep_translator-1.11.0.dist-info/RECORD
