Metadata-Version: 2.1
Name: deep-translator
Version: 1.11.0
Summary: A flexible free and unlimited python tool to translate between different languages in a simple way using multiple translators
Home-page: https://github.com/nidhaloff/deep_translator
License: MIT
Keywords: deep_translator,deepL,DeeplTranslator,translator,translation,automation,web scraping,google translator,google translation,google trans,PONS,YANDEX,MyMemory translator,Linguee,QcriTranslator,Language,Language detection,detect language,free translation,unlimited translation,translate for free
Author: Nidhal Baccouri
Author-email: nidhalbacc@gmail.com
Maintainer: Nidhal Baccouri
Maintainer-email: nidhalbacc@gmail.com
Requires-Python: >=3.7,<4.0
Classifier: Development Status :: 5 - Production/Stable
Classifier: Intended Audience :: Developers
Classifier: Intended Audience :: Education
Classifier: Intended Audience :: Information Technology
Classifier: License :: OSI Approved :: MIT License
Classifier: Operating System :: OS Independent
Classifier: Programming Language :: Python :: 3
Classifier: Programming Language :: Python :: 3.7
Classifier: Programming Language :: Python :: 3.8
Classifier: Programming Language :: Python :: 3.9
Classifier: Programming Language :: Python :: 3.10
Classifier: Programming Language :: Python :: 3.11
Classifier: Topic :: Communications
Classifier: Topic :: Education
Classifier: Topic :: Software Development
Classifier: Topic :: Text Processing
Classifier: Topic :: Text Processing :: Linguistic
Provides-Extra: ai
Provides-Extra: docx
Provides-Extra: pdf
Requires-Dist: beautifulsoup4 (>=4.9.1,<5.0.0)
Requires-Dist: docx2txt (>=0.8,<0.9) ; extra == "docx"
Requires-Dist: openai (>=0.27.6,<0.28.0) ; (python_full_version >= "3.7.1" and python_full_version < "4.0.0") and (extra == "ai")
Requires-Dist: pypdf (>=3.3.0,<4.0.0) ; extra == "pdf"
Requires-Dist: requests (>=2.23.0,<3.0.0)
Project-URL: Documentation, https://deep-translator.readthedocs.io/en/latest/
Project-URL: Repository, https://github.com/nidhaloff/deep_translator
